{
  "GeneratedUtc": "2026-07-22T14:45:17.8246950Z",
  "Campaign": {
    "RedCampaignPoints": 46,
    "BlueCampaignPoints": 2,
    "RedFactoriesDestroyed": 0,
    "BlueFactoriesDestroyed": 0,
    "RedAirfieldsDestroyed": 0,
    "BlueAirfieldsDestroyed": 0,
    "RedConvoysDestroyed": 2,
    "BlueConvoysDestroyed": 0
  },
  "Pilots": [
    {
      "Position": 1,
      "PilotKey": "twc_blacknight",
      "Pilot": "TWC_BlacKnight",
      "Rank": "Wing Commander / Major",
      "Score": 3335,
      "Sorties": 82,
      "SuccessfulSorties": 27,
      "SuccessRate": 0.3293,
      "AirKills": 32,
      "GroundKills": 0,
      "ShipKills": 0,
      "TankKills": 0,
      "TruckKills": 0,
      "AaaKills": 0,
      "ArtilleryKills": 0,
      "TrainKills": 0,
      "StaticAircraftKills": 0,
      "BuildingKills": 0,
      "OtherGroundKills": 0,
      "TotalKills": 32,
      "Deaths": 0,
      "KillDeathRatio": 32,
      "Bailouts": 0,
      "Landings": 27,
      "BombKg": 0,
      "BombingTargetsDestroyed": 0,
      "FlightMinutes": 8949.16,
      "FlightHours": 149.15,
      "LastSeenUtc": "2026-07-22 14:45:17Z"
    },
    {
      "Position": 2,
      "PilotKey": "twc_pedro",
      "Pilot": "TWC_Pedro",
      "Rank": "Flying Officer / Leutnant",
      "Score": 210,
      "Sorties": 5,
      "SuccessfulSorties": 2,
      "SuccessRate": 0.4,
      "AirKills": 2,
      "GroundKills": 0,
      "ShipKills": 0,
      "TankKills": 0,
      "TruckKills": 0,
      "AaaKills": 0,
      "ArtilleryKills": 0,
      "TrainKills": 0,
      "StaticAircraftKills": 0,
      "BuildingKills": 0,
      "OtherGroundKills": 0,
      "TotalKills": 2,
      "Deaths": 0,
      "KillDeathRatio": 2,
      "Bailouts": 0,
      "Landings": 2,
      "BombKg": 0,
      "BombingTargetsDestroyed": 0,
      "FlightMinutes": 397.85,
      "FlightHours": 6.63,
      "LastSeenUtc": "2026-07-17 23:08:33Z"
    },
    {
      "Position": 3,
      "PilotKey": "brooklynspo",
      "Pilot": "brooklynspo",
      "Rank": "Pilot Officer / Feldwebel",
      "Score": 5,
      "Sorties": 5,
      "SuccessfulSorties": 1,
      "SuccessRate": 0.2,
      "AirKills": 0,
      "GroundKills": 0,
      "ShipKills": 0,
      "TankKills": 0,
      "TruckKills": 0,
      "AaaKills": 0,
      "ArtilleryKills": 0,
      "TrainKills": 0,
      "StaticAircraftKills": 0,
      "BuildingKills": 0,
      "OtherGroundKills": 0,
      "TotalKills": 0,
      "Deaths": 0,
      "KillDeathRatio": 0,
      "Bailouts": 0,
      "Landings": 1,
      "BombKg": 0,
      "BombingTargetsDestroyed": 0,
      "FlightMinutes": 179.94,
      "FlightHours": 3,
      "LastSeenUtc": "2026-07-19 02:25:48Z"
    },
    {
      "Position": 4,
      "PilotKey": "obt~brunov",
      "Pilot": "OBT~Brunov",
      "Rank": "Pilot Officer / Feldwebel",
      "Score": 5,
      "Sorties": 1,
      "SuccessfulSorties": 1,
      "SuccessRate": 1,
      "AirKills": 0,
      "GroundKills": 0,
      "ShipKills": 0,
      "TankKills": 0,
      "TruckKills": 0,
      "AaaKills": 0,
      "ArtilleryKills": 0,
      "TrainKills": 0,
      "StaticAircraftKills": 0,
      "BuildingKills": 0,
      "OtherGroundKills": 0,
      "TotalKills": 0,
      "Deaths": 0,
      "KillDeathRatio": 0,
      "Bailouts": 0,
      "Landings": 1,
      "BombKg": 0,
      "BombingTargetsDestroyed": 0,
      "FlightMinutes": 24.04,
      "FlightHours": 0.4,
      "LastSeenUtc": "2026-07-20 20:33:11Z"
    },
    {
      "Position": 5,
      "PilotKey": "betty \\| 6-2 big-g",
      "Pilot": "Betty | 6-2 Big-G",
      "Rank": "Pilot Officer / Feldwebel",
      "Score": 0,
      "Sorties": 4,
      "SuccessfulSorties": 0,
      "SuccessRate": 0,
      "AirKills": 0,
      "GroundKills": 0,
      "ShipKills": 0,
      "TankKills": 0,
      "TruckKills": 0,
      "AaaKills": 0,
      "ArtilleryKills": 0,
      "TrainKills": 0,
      "StaticAircraftKills": 0,
      "BuildingKills": 0,
      "OtherGroundKills": 0,
      "TotalKills": 0,
      "Deaths": 0,
      "KillDeathRatio": 0,
      "Bailouts": 0,
      "Landings": 0,
      "BombKg": 0,
      "BombingTargetsDestroyed": 0,
      "FlightMinutes": 104.95,
      "FlightHours": 1.75,
      "LastSeenUtc": "2026-07-21 00:17:53Z"
    },
    {
      "Position": 6,
      "PilotKey": "joffski",
      "Pilot": "Joffski",
      "Rank": "Pilot Officer / Feldwebel",
      "Score": 0,
      "Sorties": 3,
      "SuccessfulSorties": 0,
      "SuccessRate": 0,
      "AirKills": 0,
      "GroundKills": 0,
      "ShipKills": 0,
      "TankKills": 0,
      "TruckKills": 0,
      "AaaKills": 0,
      "ArtilleryKills": 0,
      "TrainKills": 0,
      "StaticAircraftKills": 0,
      "BuildingKills": 0,
      "OtherGroundKills": 0,
      "TotalKills": 0,
      "Deaths": 0,
      "KillDeathRatio": 0,
      "Bailouts": 0,
      "Landings": 0,
      "BombKg": 0,
      "BombingTargetsDestroyed": 0,
      "FlightMinutes": 40.98,
      "FlightHours": 0.68,
      "LastSeenUtc": "2026-07-20 19:30:00Z"
    }
  ],
  "TargetDamage": [
    {
      "target": "Alert (Uxbridge) (AL,27)",
      "damagePercent": 100
    },
    {
      "target": "Bolougne_Calais Tank Convoy",
      "damagePercent": 100
    },
    {
      "target": "Calais Panzer Tank Camp",
      "damagePercent": 100
    },
    {
      "target": "ObserverUxbridge (AL,27), last station of Alert (Uxbridge),",
      "damagePercent": 100
    },
    {
      "target": "Oostende-Dunkirk Tanker Convoy",
      "damagePercent": 100
    },
    {
      "target": "Coquelles Fighter",
      "damagePercent": 98
    },
    {
      "target": "Flugplatz Abbeville",
      "damagePercent": 22
    },
    {
      "target": "Marquise West",
      "damagePercent": 3
    }
  ],
  "DestroyedTargets": [
    "Alert (Uxbridge) (AL,27)",
    "Bolougne_Calais Tank Convoy",
    "Calais Panzer Tank Camp",
    "ObserverUxbridge (AL,27), last station of Alert (Uxbridge),",
    "Oostende-Dunkirk Tanker Convoy"
  ],
  "AircraftStocks": [
    {
      "army": "LW / Blue",
      "aircraft": "Aircraft.Bf-110C-2",
      "available": 100
    },
    {
      "army": "LW / Blue",
      "aircraft": "Aircraft.Bf-110C-4",
      "available": 100
    },
    {
      "army": "LW / Blue",
      "aircraft": "Aircraft.Bf-110C-7",
      "available": 100
    },
    {
      "army": "LW / Blue",
      "aircraft": "Aircraft.G50",
      "available": 100
    },
    {
      "army": "LW / Blue",
      "aircraft": "Aircraft.He-111H-2",
      "available": 100
    },
    {
      "army": "LW / Blue",
      "aircraft": "Aircraft.He-111P-2",
      "available": 100
    },
    {
      "army": "LW / Blue",
      "aircraft": "Aircraft.Ju-87B-2",
      "available": 100
    },
    {
      "army": "LW / Blue",
      "aircraft": "Aircraft.Ju-88A-1",
      "available": 100
    },
    {
      "army": "LW / Blue",
      "aircraft": "tobruk:Aircraft.Bf-109E-7",
      "available": 97
    },
    {
      "army": "LW / Blue",
      "aircraft": "tobruk:Aircraft.Bf-109E-7N",
      "available": 100
    },
    {
      "army": "LW / Blue",
      "aircraft": "tobruk:Aircraft.Bf-109E-7Z",
      "available": 100
    },
    {
      "army": "LW / Blue",
      "aircraft": "tobruk:Aircraft.Bf-109F-1",
      "available": 200
    },
    {
      "army": "LW / Blue",
      "aircraft": "tobruk:Aircraft.Bf-109F-2",
      "available": 200
    },
    {
      "army": "LW / Blue",
      "aircraft": "tobruk:Aircraft.Bf-109F-2_Late",
      "available": 99
    },
    {
      "army": "LW / Blue",
      "aircraft": "tobruk:Aircraft.Bf-109F-4",
      "available": 99
    },
    {
      "army": "LW / Blue",
      "aircraft": "tobruk:Aircraft.Bf-110C-4N-NJG_Trop",
      "available": 100
    },
    {
      "army": "LW / Blue",
      "aircraft": "tobruk:Aircraft.D520_Serie1",
      "available": 100
    },
    {
      "army": "LW / Blue",
      "aircraft": "tobruk:Aircraft.He-111H-6",
      "available": 100
    },
    {
      "army": "LW / Blue",
      "aircraft": "tobruk:Aircraft.Ju-88A-5",
      "available": 100
    },
    {
      "army": "LW / Blue",
      "aircraft": "tobruk:Aircraft.Ju-88A-5Late",
      "available": 100
    },
    {
      "army": "LW / Blue",
      "aircraft": "tobruk:Aircraft.Ju-88C-2",
      "available": 100
    },
    {
      "army": "LW / Blue",
      "aircraft": "tobruk:Aircraft.Ju-88C-4",
      "available": 100
    },
    {
      "army": "LW / Blue",
      "aircraft": "tobruk:Aircraft.Ju-88C-4Late",
      "available": 100
    },
    {
      "army": "LW / Blue",
      "aircraft": "tobruk:Aircraft.Macchi-C202-SeriesIII",
      "available": 100
    },
    {
      "army": "LW / Blue",
      "aircraft": "tobruk:Aircraft.Macchi-C202-SeriesIII-AltoQuota",
      "available": 100
    },
    {
      "army": "LW / Blue",
      "aircraft": "tobruk:Aircraft.Macchi-C202-SeriesVII",
      "available": 100
    },
    {
      "army": "LW / Blue",
      "aircraft": "tobruk:Aircraft.Macchi-C202-SeriesVII-AltoQuota",
      "available": 100
    },
    {
      "army": "RAF / Red",
      "aircraft": "Aircraft.BlenheimMkIV_Late",
      "available": 100
    },
    {
      "army": "RAF / Red",
      "aircraft": "tobruk:Aircraft.BeaufighterMkIC",
      "available": 98
    },
    {
      "army": "RAF / Red",
      "aircraft": "tobruk:Aircraft.BeaufighterMkIF_Late",
      "available": 100
    },
    {
      "army": "RAF / Red",
      "aircraft": "tobruk:Aircraft.BeaufighterMkINF_Late",
      "available": 200
    },
    {
      "army": "RAF / Red",
      "aircraft": "tobruk:Aircraft.HurricaneMkIIb",
      "available": 100
    },
    {
      "army": "RAF / Red",
      "aircraft": "tobruk:Aircraft.HurricaneMkIIb-Late",
      "available": 200
    },
    {
      "army": "RAF / Red",
      "aircraft": "tobruk:Aircraft.HurricaneMkIIc",
      "available": 100
    },
    {
      "army": "RAF / Red",
      "aircraft": "tobruk:Aircraft.HurricaneMkIIc-Late",
      "available": 49
    },
    {
      "army": "RAF / Red",
      "aircraft": "tobruk:Aircraft.KittyhawkMkIA",
      "available": 200
    },
    {
      "army": "RAF / Red",
      "aircraft": "tobruk:Aircraft.MartletMkIII",
      "available": 100
    },
    {
      "army": "RAF / Red",
      "aircraft": "tobruk:Aircraft.SpitfireMkVa",
      "available": 100
    },
    {
      "army": "RAF / Red",
      "aircraft": "tobruk:Aircraft.SpitfireMkVb",
      "available": 194
    },
    {
      "army": "RAF / Red",
      "aircraft": "tobruk:Aircraft.SpitfireMkVb-HF",
      "available": 100
    },
    {
      "army": "RAF / Red",
      "aircraft": "tobruk:Aircraft.SpitfireMkVb-HF-Late",
      "available": 76
    },
    {
      "army": "RAF / Red",
      "aircraft": "tobruk:Aircraft.SpitfireMkVb-Late",
      "available": 100
    },
    {
      "army": "RAF / Red",
      "aircraft": "tobruk:Aircraft.TomahawkMkII",
      "available": 100
    },
    {
      "army": "RAF / Red",
      "aircraft": "tobruk:Aircraft.TomahawkMkII-Late",
      "available": 100
    },
    {
      "army": "RAF / Red",
      "aircraft": "tobruk:Aircraft.WellingtonMkIc_Late",
      "available": 91
    },
    {
      "army": "RAF / Red",
      "aircraft": "tobruk:Aircraft.WellingtonMkIc_t",
      "available": 100
    }
  ],
  "ActivePlayers": [
    {
      "pilot": "TWC_BlacKnight",
      "aircraft": "tobruk:Aircraft.WellingtonMkIc_Late"
    }
  ],
  "AirbaseRepairHours": 72,
  "DestroyedBases": []
}